{
	"info": {
		"_postman_id": "auth-service-001",
		"name": "01. Auth Service (5 endpoints)",
		"description": "Authentication service - Register, Login, Token management",
		"schema": "https://schema.getpostman.com/json/collection/v2.1.0/collection.json"
	},
	"item": [
		{
			"name": "Register",
			"event": [
				{
					"listen": "test",
					"script": {
						"exec": [
							"if (pm.response.code === 200 || pm.response.code === 201) {",
							"    var jsonData = pm.response.json();",
							"    if (jsonData.accessToken) {",
							"        pm.environment.set(\"access_token\", jsonData.accessToken);",
							"    }",
							"    if (jsonData.refreshToken) {",
							"        pm.environment.set(\"refresh_token\", jsonData.refreshToken);",
							"    }",
							"    if (jsonData.userId) {",
							"        pm.environment.set(\"user_id\", jsonData.userId);",
							"    }",
							"}"
						],
						"type": "text/javascript"
					}
				}
			],
			"request": {
				"auth": {
					"type": "noauth"
				},
				"method": "POST",
				"header": [
					{
						"key": "Content-Type",
						"value": "application/json"
					}
				],
				"body": {
					"mode": "raw",
					"raw": "{\n  \"email\": \"newuser@example.com\",\n  \"password\": \"password123\",\n  \"fullName\": \"New User\",\n  \"roleId\": 1,\n  \"dateOfBirth\": \"1990-01-01\",\n  \"address\": \"123 Main St\",\n  \"isStudying\": true\n}"
				},
				"url": {
					"raw": "{{base_url}}/auth/register",
					"host": ["{{base_url}}"],
					"path": ["auth", "register"]
				},
				"description": "Register new user account. Returns JWT tokens. **Required**: email (valid format), password (6-50 chars). **Optional**: fullName, roleId or roleName, dateOfBirth, address, isStudying"
			},
			"response": []
		},
		{
			"name": "Login",
			"event": [
				{
					"listen": "test",
					"script": {
						"exec": [
							"if (pm.response.code === 200) {",
							"    var jsonData = pm.response.json();",
							"    if (jsonData.accessToken) {",
							"        pm.environment.set(\"access_token\", jsonData.accessToken);",
							"        console.log(\"✓ Access token saved\");",
							"    }",
							"    if (jsonData.refreshToken) {",
							"        pm.environment.set(\"refresh_token\", jsonData.refreshToken);",
							"        console.log(\"✓ Refresh token saved\");",
							"    }",
							"    if (jsonData.userId) {",
							"        pm.environment.set(\"user_id\", jsonData.userId);",
							"        console.log(\"✓ User ID saved: \" + jsonData.userId);",
							"    }",
							"}"
						],
						"type": "text/javascript"
					}
				}
			],
			"request": {
				"auth": {
					"type": "noauth"
				},
				"method": "POST",
				"header": [
					{
						"key": "Content-Type",
						"value": "application/json"
					}
				],
				"body": {
					"mode": "raw",
					"raw": "{\n  \"email\": \"admin@example.com\",\n  \"password\": \"admin123\"\n}"
				},
				"url": {
					"raw": "{{base_url}}/auth/login",
					"host": ["{{base_url}}"],
					"path": ["auth", "login"]
				},
				"description": "Login with email and password. Returns access token, refresh token, and user ID. **All fields required**: email (valid format), password"
			},
			"response": []
		},
		{
			"name": "Refresh Token",
			"event": [
				{
					"listen": "test",
					"script": {
						"exec": [
							"if (pm.response.code === 200) {",
							"    var jsonData = pm.response.json();",
							"    if (jsonData.accessToken) {",
							"        pm.environment.set(\"access_token\", jsonData.accessToken);",
							"        console.log(\"✓ New access token saved\");",
							"    }",
							"}"
						],
						"type": "text/javascript"
					}
				}
			],
			"request": {
				"auth": {
					"type": "noauth"
				},
				"method": "POST",
				"header": [
					{
						"key": "Content-Type",
						"value": "application/json"
					}
				],
				"body": {
					"mode": "raw",
					"raw": "{\n  \"refreshToken\": \"{{refresh_token}}\"\n}"
				},
				"url": {
					"raw": "{{base_url}}/auth/refresh",
					"host": ["{{base_url}}"],
					"path": ["auth", "refresh"]
				},
				"description": "Refresh access token using refresh token. Returns new access token."
			},
			"response": []
		},
		{
			"name": "Verify Token",
			"request": {
				"auth": {
					"type": "noauth"
				},
				"method": "GET",
				"header": [],
				"url": {
					"raw": "{{base_url}}/auth/verify?token={{access_token}}",
					"host": ["{{base_url}}"],
					"path": ["auth", "verify"],
					"query": [
						{
							"key": "token",
							"value": "{{access_token}}",
							"description": "JWT token to verify"
						}
					]
				},
				"description": "Verify if a JWT token is valid. Returns token claims if valid."
			},
			"response": []
		},
		{
			"name": "Get User Info",
			"request": {
				"method": "GET",
				"header": [
					{
						"key": "Authorization",
						"value": "Bearer {{access_token}}",
						"type": "text"
					}
				],
				"url": {
					"raw": "{{base_url}}/auth/user-info",
					"host": ["{{base_url}}"],
					"path": ["auth", "user-info"]
				},
				"description": "Get user information from JWT token. Requires Bearer token in Authorization header."
			},
			"response": []
		}
	],
	"auth": {
		"type": "bearer",
		"bearer": [
			{
				"key": "token",
				"value": "{{access_token}}",
				"type": "string"
			}
		]
	}
}
