{
	"info": {
		"_postman_id": "abc-interview-microservice",
		"name": "Interview Microservice ABC",
		"description": "Complete API collection for Interview Microservice ABC platform",
		"schema": "https://schema.getpostman.com/json/collection/v2.1.0/collection.json"
	},
	"item": [
		{
			"name": "Auth Service",
			"item": [
				{
					"name": "Register",
					"request": {
						"method": "POST",
						"header": [
							{
								"key": "Content-Type",
								"value": "application/json"
							}
						],
						"body": {
							"mode": "raw",
							"raw": "{\n  \"email\": \"user@example.com\",\n  \"password\": \"password123\",\n  \"fullName\": \"John Doe\",\n  \"roleName\": \"USER\"\n}"
						},
						"url": {
							"raw": "{{baseUrl}}/auth/register",
							"host": ["{{baseUrl}}"],
							"path": ["auth", "register"]
						}
					}
				},
				{
					"name": "Login",
					"request": {
						"method": "POST",
						"header": [
							{
								"key": "Content-Type",
								"value": "application/json"
							}
						],
						"body": {
							"mode": "raw",
							"raw": "{\n  \"email\": \"user@example.com\",\n  \"password\": \"password123\"\n}"
						},
						"url": {
							"raw": "{{baseUrl}}/auth/login",
							"host": ["{{baseUrl}}"],
							"path": ["auth", "login"]
						}
					}
				},
				{
					"name": "Refresh Token",
					"request": {
						"method": "POST",
						"header": [
							{
								"key": "Content-Type",
								"value": "application/json"
							}
						],
						"body": {
							"mode": "raw",
							"raw": "{\n  \"refreshToken\": \"your_refresh_token_here\"\n}"
						},
						"url": {
							"raw": "{{baseUrl}}/auth/refresh",
							"host": ["{{baseUrl}}"],
							"path": ["auth", "refresh"]
						}
					}
				},
				{
					"name": "Verify Token",
					"request": {
						"method": "GET",
						"url": {
							"raw": "{{baseUrl}}/auth/verify?token={{token}}",
							"host": ["{{baseUrl}}"],
							"path": ["auth", "verify"],
							"query": [
								{
									"key": "token",
									"value": "{{token}}"
								}
							]
						}
					}
				},
				{
					"name": "Get User by ID",
					"request": {
						"method": "GET",
						"url": {
							"raw": "{{baseUrl}}/auth/users/{{userId}}",
							"host": ["{{baseUrl}}"],
							"path": ["auth", "users", "{{userId}}"]
						}
					}
				}
			]
		},
		{
			"name": "User Service",
			"item": [
				{
					"name": "Register User",
					"request": {
						"method": "POST",
						"header": [
							{
								"key": "Content-Type",
								"value": "application/json"
							}
						],
						"body": {
							"mode": "raw",
							"raw": "{\n  \"email\": \"user@example.com\",\n  \"password\": \"password123\",\n  \"fullName\": \"John Doe\",\n  \"dateOfBirth\": \"1990-01-01\",\n  \"address\": \"123 Main St\",\n  \"isStudying\": true\n}"
						},
						"url": {
							"raw": "{{baseUrl}}/users/register",
							"host": ["{{baseUrl}}"],
							"path": ["users", "register"]
						}
					}
				},
				{
					"name": "Get User by ID",
					"request": {
						"method": "GET",
						"url": {
							"raw": "{{baseUrl}}/users/{{userId}}",
							"host": ["{{baseUrl}}"],
							"path": ["users", "{{userId}}"]
						}
					}
				},
				{
					"name": "Login User",
					"request": {
						"method": "POST",
						"header": [
							{
								"key": "Content-Type",
								"value": "application/json"
							}
						],
						"body": {
							"mode": "raw",
							"raw": "{\n  \"email\": \"user@example.com\",\n  \"password\": \"password123\"\n}"
						},
						"url": {
							"raw": "{{baseUrl}}/users/login",
							"host": ["{{baseUrl}}"],
							"path": ["users", "login"]
						}
					}
				},
				{
					"name": "Verify User",
					"request": {
						"method": "GET",
						"url": {
							"raw": "{{baseUrl}}/users/verify?token={{token}}",
							"host": ["{{baseUrl}}"],
							"path": ["users", "verify"],
							"query": [
								{
									"key": "token",
									"value": "{{token}}"
								}
							]
						}
					}
				},
				{
					"name": "Update User Role",
					"request": {
						"method": "PUT",
						"header": [
							{
								"key": "Content-Type",
								"value": "application/json"
							},
							{
								"key": "Authorization",
								"value": "Bearer {{adminToken}}"
							}
						],
						"body": {
							"mode": "raw",
							"raw": "{\n  \"roleName\": \"ADMIN\"\n}"
						},
						"url": {
							"raw": "{{baseUrl}}/users/{{userId}}/role",
							"host": ["{{baseUrl}}"],
							"path": ["users", "{{userId}}", "role"]
						}
					}
				},
				{
					"name": "Update User Status",
					"request": {
						"method": "PUT",
						"header": [
							{
								"key": "Content-Type",
								"value": "application/json"
							},
							{
								"key": "Authorization",
								"value": "Bearer {{adminToken}}"
							}
						],
						"body": {
							"mode": "raw",
							"raw": "{\n  \"status\": \"ACTIVE\"\n}"
						},
						"url": {
							"raw": "{{baseUrl}}/users/{{userId}}/status",
							"host": ["{{baseUrl}}"],
							"path": ["users", "{{userId}}", "status"]
						}
					}
				},
				{
					"name": "Apply Elo Score",
					"request": {
						"method": "POST",
						"header": [
							{
								"key": "Content-Type",
								"value": "application/json"
							}
						],
						"body": {
							"mode": "raw",
							"raw": "{\n  \"userId\": 1,\n  \"action\": \"EXAM_COMPLETED\",\n  \"points\": 50,\n  \"description\": \"Completed exam successfully\"\n}"
						},
						"url": {
							"raw": "{{baseUrl}}/users/elo",
							"host": ["{{baseUrl}}"],
							"path": ["users", "elo"]
						}
					}
				}
			]
		},
		{
			"name": "Question Service",
			"item": [
				{
					"name": "Taxonomy Management",
					"item": [
						{
							"name": "Create Field",
							"request": {
								"method": "POST",
								"header": [
									{
										"key": "Content-Type",
										"value": "application/json"
									},
									{
										"key": "Authorization",
										"value": "Bearer {{adminToken}}"
									}
								],
								"body": {
									"mode": "raw",
									"raw": "{\n  \"fieldName\": \"Lập trình viên\",\n  \"description\": \"Ngành lập trình phần mềm\"\n}"
								},
								"url": {
									"raw": "{{baseUrl}}/fields",
									"host": ["{{baseUrl}}"],
									"path": ["fields"]
								}
							}
						},
						{
							"name": "Create Topic",
							"request": {
								"method": "POST",
								"header": [
									{
										"key": "Content-Type",
										"value": "application/json"
									},
									{
										"key": "Authorization",
										"value": "Bearer {{adminToken}}"
									}
								],
								"body": {
									"mode": "raw",
									"raw": "{\n  \"fieldId\": 1,\n  \"topicName\": \"ReactJS\",\n  \"description\": \"Thư viện JavaScript cho UI\"\n}"
								},
								"url": {
									"raw": "{{baseUrl}}/topics",
									"host": ["{{baseUrl}}"],
									"path": ["topics"]
								}
							}
						},
						{
							"name": "Create Level",
							"request": {
								"method": "POST",
								"header": [
									{
										"key": "Content-Type",
										"value": "application/json"
									},
									{
										"key": "Authorization",
										"value": "Bearer {{adminToken}}"
									}
								],
								"body": {
									"mode": "raw",
									"raw": "{\n  \"levelName\": \"Junior\",\n  \"description\": \"1-2 năm kinh nghiệm\"\n}"
								},
								"url": {
									"raw": "{{baseUrl}}/levels",
									"host": ["{{baseUrl}}"],
									"path": ["levels"]
								}
							}
						},
						{
							"name": "Create Question Type",
							"request": {
								"method": "POST",
								"header": [
									{
										"key": "Content-Type",
										"value": "application/json"
									},
									{
										"key": "Authorization",
										"value": "Bearer {{adminToken}}"
									}
								],
								"body": {
									"mode": "raw",
									"raw": "{\n  \"questionTypeName\": \"Multiple Choice\",\n  \"description\": \"Câu hỏi trắc nghiệm\"\n}"
								},
								"url": {
									"raw": "{{baseUrl}}/question-types",
									"host": ["{{baseUrl}}"],
									"path": ["question-types"]
								}
							}
						}
					]
				},
				{
					"name": "Question Management",
					"item": [
						{
							"name": "Create Question",
							"request": {
								"method": "POST",
								"header": [
									{
										"key": "Content-Type",
										"value": "application/json"
									},
									{
										"key": "Authorization",
										"value": "Bearer {{userToken}}"
									}
								],
								"body": {
									"mode": "raw",
									"raw": "{\n  \"userId\": 1,\n  \"topicId\": 1,\n  \"fieldId\": 1,\n  \"levelId\": 1,\n  \"questionTypeId\": 1,\n  \"questionContent\": \"What is ReactJS?\",\n  \"questionAnswer\": \"ReactJS is a JavaScript library for building user interfaces\",\n  \"language\": \"en\"\n}"
								},
								"url": {
									"raw": "{{baseUrl}}/questions",
									"host": ["{{baseUrl}}"],
									"path": ["questions"]
								}
							}
						},
						{
							"name": "Get Question by ID",
							"request": {
								"method": "GET",
								"url": {
									"raw": "{{baseUrl}}/questions/{{questionId}}",
									"host": ["{{baseUrl}}"],
									"path": ["questions", "{{questionId}}"]
								}
							}
						},
						{
							"name": "Update Question",
							"request": {
								"method": "PUT",
								"header": [
									{
										"key": "Content-Type",
										"value": "application/json"
									},
									{
										"key": "Authorization",
										"value": "Bearer {{userToken}}"
									}
								],
								"body": {
									"mode": "raw",
									"raw": "{\n  \"userId\": 1,\n  \"topicId\": 1,\n  \"fieldId\": 1,\n  \"levelId\": 1,\n  \"questionTypeId\": 1,\n  \"questionContent\": \"What is ReactJS and its main features?\",\n  \"questionAnswer\": \"ReactJS is a JavaScript library for building user interfaces with features like virtual DOM, component-based architecture, and JSX\",\n  \"language\": \"en\"\n}"
								},
								"url": {
									"raw": "{{baseUrl}}/questions/{{questionId}}",
									"host": ["{{baseUrl}}"],
									"path": ["questions", "{{questionId}}"]
								}
							}
						},
						{
							"name": "Delete Question",
							"request": {
								"method": "DELETE",
								"header": [
									{
										"key": "Authorization",
										"value": "Bearer {{adminToken}}"
									}
								],
								"url": {
									"raw": "{{baseUrl}}/questions/{{questionId}}",
									"host": ["{{baseUrl}}"],
									"path": ["questions", "{{questionId}}"]
								}
							}
						},
						{
							"name": "Approve Question",
							"request": {
								"method": "POST",
								"header": [
									{
										"key": "Authorization",
										"value": "Bearer {{adminToken}}"
									}
								],
								"url": {
									"raw": "{{baseUrl}}/questions/{{questionId}}/approve?adminId={{adminId}}",
									"host": ["{{baseUrl}}"],
									"path": ["questions", "{{questionId}}", "approve"],
									"query": [
										{
											"key": "adminId",
											"value": "{{adminId}}"
										}
									]
								}
							}
						},
						{
							"name": "Reject Question",
							"request": {
								"method": "POST",
								"header": [
									{
										"key": "Authorization",
										"value": "Bearer {{adminToken}}"
									}
								],
								"url": {
									"raw": "{{baseUrl}}/questions/{{questionId}}/reject?adminId={{adminId}}",
									"host": ["{{baseUrl}}"],
									"path": ["questions", "{{questionId}}", "reject"],
									"query": [
										{
											"key": "adminId",
											"value": "{{adminId}}"
										}
									]
								}
							}
						},
						{
							"name": "List Questions by Topic",
							"request": {
								"method": "GET",
								"url": {
									"raw": "{{baseUrl}}/topics/{{topicId}}/questions?page=0&size=10",
									"host": ["{{baseUrl}}"],
									"path": ["topics", "{{topicId}}", "questions"],
									"query": [
										{
											"key": "page",
											"value": "0"
										},
										{
											"key": "size",
											"value": "10"
										}
									]
								}
							}
						}
					]
				},
				{
					"name": "Answer Management",
					"item": [
						{
							"name": "Create Answer",
							"request": {
								"method": "POST",
								"header": [
									{
										"key": "Content-Type",
										"value": "application/json"
									},
									{
										"key": "Authorization",
										"value": "Bearer {{userToken}}"
									}
								],
								"body": {
									"mode": "raw",
									"raw": "{\n  \"userId\": 1,\n  \"questionId\": 1,\n  \"questionTypeId\": 1,\n  \"answerContent\": \"ReactJS is a JavaScript library for building user interfaces\",\n  \"isCorrect\": true,\n  \"orderNumber\": 1\n}"
								},
								"url": {
									"raw": "{{baseUrl}}/answers",
									"host": ["{{baseUrl}}"],
									"path": ["answers"]
								}
							}
						},
						{
							"name": "Get Answer by ID",
							"request": {
								"method": "GET",
								"url": {
									"raw": "{{baseUrl}}/answers/{{answerId}}",
									"host": ["{{baseUrl}}"],
									"path": ["answers", "{{answerId}}"]
								}
							}
						},
						{
							"name": "Update Answer",
							"request": {
								"method": "PUT",
								"header": [
									{
										"key": "Content-Type",
										"value": "application/json"
									},
									{
										"key": "Authorization",
										"value": "Bearer {{userToken}}"
									}
								],
								"body": {
									"mode": "raw",
									"raw": "{\n  \"userId\": 1,\n  \"questionId\": 1,\n  \"questionTypeId\": 1,\n  \"answerContent\": \"ReactJS is a JavaScript library for building user interfaces with virtual DOM\",\n  \"isCorrect\": true,\n  \"orderNumber\": 1\n}"
								},
								"url": {
									"raw": "{{baseUrl}}/answers/{{answerId}}",
									"host": ["{{baseUrl}}"],
									"path": ["answers", "{{answerId}}"]
								}
							}
						},
						{
							"name": "Delete Answer",
							"request": {
								"method": "DELETE",
								"header": [
									{
										"key": "Authorization",
										"value": "Bearer {{adminToken}}"
									}
								],
								"url": {
									"raw": "{{baseUrl}}/answers/{{answerId}}",
									"host": ["{{baseUrl}}"],
									"path": ["answers", "{{answerId}}"]
								}
							}
						},
						{
							"name": "Mark Sample Answer",
							"request": {
								"method": "POST",
								"header": [
									{
										"key": "Authorization",
										"value": "Bearer {{adminToken}}"
									}
								],
								"url": {
									"raw": "{{baseUrl}}/answers/{{answerId}}/sample?isSample=true",
									"host": ["{{baseUrl}}"],
									"path": ["answers", "{{answerId}}", "sample"],
									"query": [
										{
											"key": "isSample",
											"value": "true"
										}
									]
								}
							}
						},
						{
							"name": "List Answers by Question",
							"request": {
								"method": "GET",
								"url": {
									"raw": "{{baseUrl}}/questions/{{questionId}}/answers?page=0&size=10",
									"host": ["{{baseUrl}}"],
									"path": ["questions", "{{questionId}}", "answers"],
									"query": [
										{
											"key": "page",
											"value": "0"
										},
										{
											"key": "size",
											"value": "10"
										}
									]
								}
							}
						}
					]
				}
			]
		},
		{
			"name": "Exam Service",
			"item": [
				{
					"name": "Exam Management",
					"item": [
						{
							"name": "Create Exam",
							"request": {
								"method": "POST",
								"header": [
									{
										"key": "Content-Type",
										"value": "application/json"
									},
									{
										"key": "Authorization",
										"value": "Bearer {{userToken}}"
									}
								],
								"body": {
									"mode": "raw",
									"raw": "{\n  \"userId\": 1,\n  \"examType\": \"TECHNICAL\",\n  \"title\": \"ReactJS Developer Test\",\n  \"position\": \"Frontend Developer\",\n  \"topics\": \"[1,2,3]\",\n  \"questionTypes\": \"[1,2]\",\n  \"questionCount\": 20,\n  \"duration\": 60,\n  \"language\": \"en\"\n}"
								},
								"url": {
									"raw": "{{baseUrl}}/exams",
									"host": ["{{baseUrl}}"],
									"path": ["exams"]
								}
							}
						},
						{
							"name": "Get Exam by ID",
							"request": {
								"method": "GET",
								"url": {
									"raw": "{{baseUrl}}/exams/{{examId}}",
									"host": ["{{baseUrl}}"],
									"path": ["exams", "{{examId}}"]
								}
							}
						},
						{
							"name": "Update Exam",
							"request": {
								"method": "PUT",
								"header": [
									{
										"key": "Content-Type",
										"value": "application/json"
									},
									{
										"key": "Authorization",
										"value": "Bearer {{userToken}}"
									}
								],
								"body": {
									"mode": "raw",
									"raw": "{\n  \"userId\": 1,\n  \"examType\": \"TECHNICAL\",\n  \"title\": \"Advanced ReactJS Developer Test\",\n  \"position\": \"Senior Frontend Developer\",\n  \"topics\": \"[1,2,3,4]\",\n  \"questionTypes\": \"[1,2,3]\",\n  \"questionCount\": 25,\n  \"duration\": 90,\n  \"language\": \"en\"\n}"
								},
								"url": {
									"raw": "{{baseUrl}}/exams/{{examId}}",
									"host": ["{{baseUrl}}"],
									"path": ["exams", "{{examId}}"]
								}
							}
						},
						{
							"name": "Delete Exam",
							"request": {
								"method": "DELETE",
								"header": [
									{
										"key": "Authorization",
										"value": "Bearer {{adminToken}}"
									}
								],
								"url": {
									"raw": "{{baseUrl}}/exams/{{examId}}",
									"host": ["{{baseUrl}}"],
									"path": ["exams", "{{examId}}"]
								}
							}
						},
						{
							"name": "Publish Exam",
							"request": {
								"method": "POST",
								"header": [
									{
										"key": "Authorization",
										"value": "Bearer {{adminToken}}"
									}
								],
								"url": {
									"raw": "{{baseUrl}}/exams/{{examId}}/publish?userId={{adminId}}",
									"host": ["{{baseUrl}}"],
									"path": ["exams", "{{examId}}", "publish"],
									"query": [
										{
											"key": "userId",
											"value": "{{adminId}}"
										}
									]
								}
							}
						},
						{
							"name": "Start Exam",
							"request": {
								"method": "POST",
								"header": [
									{
										"key": "Authorization",
										"value": "Bearer {{userToken}}"
									}
								],
								"url": {
									"raw": "{{baseUrl}}/exams/{{examId}}/start",
									"host": ["{{baseUrl}}"],
									"path": ["exams", "{{examId}}", "start"]
								}
							}
						},
						{
							"name": "Complete Exam",
							"request": {
								"method": "POST",
								"header": [
									{
										"key": "Authorization",
										"value": "Bearer {{userToken}}"
									}
								],
								"url": {
									"raw": "{{baseUrl}}/exams/{{examId}}/complete",
									"host": ["{{baseUrl}}"],
									"path": ["exams", "{{examId}}", "complete"]
								}
							}
						},
						{
							"name": "List Exams by User",
							"request": {
								"method": "GET",
								"header": [
									{
										"key": "Authorization",
										"value": "Bearer {{userToken}}"
									}
								],
								"url": {
									"raw": "{{baseUrl}}/exams/user/{{userId}}?page=0&size=10",
									"host": ["{{baseUrl}}"],
									"path": ["exams", "user", "{{userId}}"],
									"query": [
										{
											"key": "page",
											"value": "0"
										},
										{
											"key": "size",
											"value": "10"
										}
									]
								}
							}
						},
						{
							"name": "List Exams by Type",
							"request": {
								"method": "GET",
								"url": {
									"raw": "{{baseUrl}}/exams/type/{{examType}}?page=0&size=10",
									"host": ["{{baseUrl}}"],
									"path": ["exams", "type", "{{examType}}"],
									"query": [
										{
											"key": "page",
											"value": "0"
										},
										{
											"key": "size",
											"value": "10"
										}
									]
								}
							}
						}
					]
				},
				{
					"name": "Exam Questions",
					"item": [
						{
							"name": "Add Question to Exam",
							"request": {
								"method": "POST",
								"header": [
									{
										"key": "Content-Type",
										"value": "application/json"
									},
									{
										"key": "Authorization",
										"value": "Bearer {{adminToken}}"
									}
								],
								"body": {
									"mode": "raw",
									"raw": "{\n  \"examId\": 1,\n  \"questionId\": 1,\n  \"orderNumber\": 1\n}"
								},
								"url": {
									"raw": "{{baseUrl}}/exams/questions",
									"host": ["{{baseUrl}}"],
									"path": ["exams", "questions"]
								}
							}
						},
						{
							"name": "Remove Questions from Exam",
							"request": {
								"method": "DELETE",
								"header": [
									{
										"key": "Authorization",
										"value": "Bearer {{adminToken}}"
									}
								],
								"url": {
									"raw": "{{baseUrl}}/exams/{{examId}}/questions",
									"host": ["{{baseUrl}}"],
									"path": ["exams", "{{examId}}", "questions"]
								}
							}
						}
					]
				},
				{
					"name": "Exam Results",
					"item": [
						{
							"name": "Submit Result",
							"request": {
								"method": "POST",
								"header": [
									{
										"key": "Content-Type",
										"value": "application/json"
									},
									{
										"key": "Authorization",
										"value": "Bearer {{userToken}}"
									}
								],
								"body": {
									"mode": "raw",
									"raw": "{\n  \"examId\": 1,\n  \"userId\": 1,\n  \"score\": 85.5,\n  \"passStatus\": true,\n  \"feedback\": \"Good performance, well done!\"\n}"
								},
								"url": {
									"raw": "{{baseUrl}}/exams/results",
									"host": ["{{baseUrl}}"],
									"path": ["exams", "results"]
								}
							}
						},
						{
							"name": "Get Result by ID",
							"request": {
								"method": "GET",
								"header": [
									{
										"key": "Authorization",
										"value": "Bearer {{userToken}}"
									}
								],
								"url": {
									"raw": "{{baseUrl}}/exams/results/{{resultId}}",
									"host": ["{{baseUrl}}"],
									"path": ["exams", "results", "{{resultId}}"]
								}
							}
						},
						{
							"name": "List Results by Exam",
							"request": {
								"method": "GET",
								"header": [
									{
										"key": "Authorization",
										"value": "Bearer {{adminToken}}"
									}
								],
								"url": {
									"raw": "{{baseUrl}}/exams/{{examId}}/results?page=0&size=10",
									"host": ["{{baseUrl}}"],
									"path": ["exams", "{{examId}}", "results"],
									"query": [
										{
											"key": "page",
											"value": "0"
										},
										{
											"key": "size",
											"value": "10"
										}
									]
								}
							}
						},
						{
							"name": "List Results by User",
							"request": {
								"method": "GET",
								"header": [
									{
										"key": "Authorization",
										"value": "Bearer {{userToken}}"
									}
								],
								"url": {
									"raw": "{{baseUrl}}/exams/results/user/{{userId}}?page=0&size=10",
									"host": ["{{baseUrl}}"],
									"path": ["exams", "results", "user", "{{userId}}"],
									"query": [
										{
											"key": "page",
											"value": "0"
										},
										{
											"key": "size",
											"value": "10"
										}
									]
								}
							}
						}
					]
				},
				{
					"name": "User Answers",
					"item": [
						{
							"name": "Submit Answer",
							"request": {
								"method": "POST",
								"header": [
									{
										"key": "Content-Type",
										"value": "application/json"
									},
									{
										"key": "Authorization",
										"value": "Bearer {{userToken}}"
									}
								],
								"body": {
									"mode": "raw",
									"raw": "{\n  \"examId\": 1,\n  \"questionId\": 1,\n  \"userId\": 1,\n  \"answerContent\": \"ReactJS is a JavaScript library for building user interfaces\",\n  \"isCorrect\": true\n}"
								},
								"url": {
									"raw": "{{baseUrl}}/exams/answers",
									"host": ["{{baseUrl}}"],
									"path": ["exams", "answers"]
								}
							}
						},
						{
							"name": "Get User Answer by ID",
							"request": {
								"method": "GET",
								"header": [
									{
										"key": "Authorization",
										"value": "Bearer {{userToken}}"
									}
								],
								"url": {
									"raw": "{{baseUrl}}/exams/answers/{{answerId}}",
									"host": ["{{baseUrl}}"],
									"path": ["exams", "answers", "{{answerId}}"]
								}
							}
						},
						{
							"name": "Get User Answers by Exam",
							"request": {
								"method": "GET",
								"header": [
									{
										"key": "Authorization",
										"value": "Bearer {{userToken}}"
									}
								],
								"url": {
									"raw": "{{baseUrl}}/exams/{{examId}}/answers/{{userId}}?page=0&size=10",
									"host": ["{{baseUrl}}"],
									"path": ["exams", "{{examId}}", "answers", "{{userId}}"],
									"query": [
										{
											"key": "page",
											"value": "0"
										},
										{
											"key": "size",
											"value": "10"
										}
									]
								}
							}
						}
					]
				},
				{
					"name": "Exam Registration",
					"item": [
						{
							"name": "Register for Exam",
							"request": {
								"method": "POST",
								"header": [
									{
										"key": "Content-Type",
										"value": "application/json"
									},
									{
										"key": "Authorization",
										"value": "Bearer {{userToken}}"
									}
								],
								"body": {
									"mode": "raw",
									"raw": "{\n  \"examId\": 1,\n  \"userId\": 1\n}"
								},
								"url": {
									"raw": "{{baseUrl}}/exams/registrations",
									"host": ["{{baseUrl}}"],
									"path": ["exams", "registrations"]
								}
							}
						},
						{
							"name": "Cancel Registration",
							"request": {
								"method": "POST",
								"header": [
									{
										"key": "Authorization",
										"value": "Bearer {{userToken}}"
									}
								],
								"url": {
									"raw": "{{baseUrl}}/exams/registrations/{{registrationId}}/cancel",
									"host": ["{{baseUrl}}"],
									"path": ["exams", "registrations", "{{registrationId}}", "cancel"]
								}
							}
						},
						{
							"name": "Get Registration by ID",
							"request": {
								"method": "GET",
								"header": [
									{
										"key": "Authorization",
										"value": "Bearer {{userToken}}"
									}
								],
								"url": {
									"raw": "{{baseUrl}}/exams/registrations/{{registrationId}}",
									"host": ["{{baseUrl}}"],
									"path": ["exams", "registrations", "{{registrationId}}"]
								}
							}
						},
						{
							"name": "List Registrations by Exam",
							"request": {
								"method": "GET",
								"header": [
									{
										"key": "Authorization",
										"value": "Bearer {{adminToken}}"
									}
								],
								"url": {
									"raw": "{{baseUrl}}/exams/{{examId}}/registrations?page=0&size=10",
									"host": ["{{baseUrl}}"],
									"path": ["exams", "{{examId}}", "registrations"],
									"query": [
										{
											"key": "page",
											"value": "0"
										},
										{
											"key": "size",
											"value": "10"
										}
									]
								}
							}
						},
						{
							"name": "List Registrations by User",
							"request": {
								"method": "GET",
								"header": [
									{
										"key": "Authorization",
										"value": "Bearer {{userToken}}"
									}
								],
								"url": {
									"raw": "{{baseUrl}}/exams/registrations/user/{{userId}}?page=0&size=10",
									"host": ["{{baseUrl}}"],
									"path": ["exams", "registrations", "user", "{{userId}}"],
									"query": [
										{
											"key": "page",
											"value": "0"
										},
										{
											"key": "size",
											"value": "10"
										}
									]
								}
							}
						}
					]
				}
			]
		},
		{
			"name": "Career Service",
			"item": [
				{
					"name": "Create Career Preference",
					"request": {
						"method": "POST",
						"header": [
							{
								"key": "Content-Type",
								"value": "application/json"
							},
							{
								"key": "Authorization",
								"value": "Bearer {{userToken}}"
							}
						],
						"body": {
							"mode": "raw",
							"raw": "{\n  \"userId\": 1,\n  \"fieldId\": 1,\n  \"topicId\": 1\n}"
						},
						"url": {
							"raw": "{{baseUrl}}/career",
							"host": ["{{baseUrl}}"],
							"path": ["career"]
						}
					}
				},
				{
					"name": "Update Career Preference",
					"request": {
						"method": "PUT",
						"header": [
							{
								"key": "Content-Type",
								"value": "application/json"
							},
							{
								"key": "Authorization",
								"value": "Bearer {{userToken}}"
							}
						],
						"body": {
							"mode": "raw",
							"raw": "{\n  \"userId\": 1,\n  \"fieldId\": 2,\n  \"topicId\": 3\n}"
						},
						"url": {
							"raw": "{{baseUrl}}/career/update/{{careerId}}",
							"host": ["{{baseUrl}}"],
							"path": ["career", "update", "{{careerId}}"]
						}
					}
				},
				{
					"name": "Get Career by ID",
					"request": {
						"method": "GET",
						"header": [
							{
								"key": "Authorization",
								"value": "Bearer {{userToken}}"
							}
						],
						"url": {
							"raw": "{{baseUrl}}/career/{{careerId}}",
							"host": ["{{baseUrl}}"],
							"path": ["career", "{{careerId}}"]
						}
					}
				},
				{
					"name": "Get Career by User ID",
					"request": {
						"method": "GET",
						"header": [
							{
								"key": "Authorization",
								"value": "Bearer {{userToken}}"
							}
						],
						"url": {
							"raw": "{{baseUrl}}/career/preferences/{{userId}}?page=0&size=10",
							"host": ["{{baseUrl}}"],
							"path": ["career", "preferences", "{{userId}}"],
							"query": [
								{
									"key": "page",
									"value": "0"
								},
								{
									"key": "size",
									"value": "10"
								}
							]
						}
					}
				},
				{
					"name": "Delete Career Preference",
					"request": {
						"method": "DELETE",
						"header": [
							{
								"key": "Authorization",
								"value": "Bearer {{userToken}}"
							}
						],
						"url": {
							"raw": "{{baseUrl}}/career/{{careerId}}",
							"host": ["{{baseUrl}}"],
							"path": ["career", "{{careerId}}"]
						}
					}
				}
			]
		},
		{
			"name": "News Service",
			"item": [
				{
					"name": "News Management",
					"item": [
						{
							"name": "Create News",
							"request": {
								"method": "POST",
								"header": [
									{
										"key": "Content-Type",
										"value": "application/json"
									},
									{
										"key": "Authorization",
										"value": "Bearer {{userToken}}"
									}
								],
								"body": {
									"mode": "raw",
									"raw": "{\n  \"userId\": 1,\n  \"title\": \"New ReactJS Features Released\",\n  \"content\": \"ReactJS 18 introduces new features like concurrent rendering and automatic batching\",\n  \"fieldId\": 1,\n  \"newsType\": \"NEWS\"\n}"
								},
								"url": {
									"raw": "{{baseUrl}}/news",
									"host": ["{{baseUrl}}"],
									"path": ["news"]
								}
							}
						},
						{
							"name": "Get News by ID",
							"request": {
								"method": "GET",
								"url": {
									"raw": "{{baseUrl}}/news/{{newsId}}",
									"host": ["{{baseUrl}}"],
									"path": ["news", "{{newsId}}"]
								}
							}
						},
						{
							"name": "Update News",
							"request": {
								"method": "PUT",
								"header": [
									{
										"key": "Content-Type",
										"value": "application/json"
									},
									{
										"key": "Authorization",
										"value": "Bearer {{userToken}}"
									}
								],
								"body": {
									"mode": "raw",
									"raw": "{\n  \"userId\": 1,\n  \"title\": \"Updated: New ReactJS Features Released\",\n  \"content\": \"ReactJS 18 introduces new features like concurrent rendering, automatic batching, and improved performance\",\n  \"fieldId\": 1,\n  \"newsType\": \"NEWS\"\n}"
								},
								"url": {
									"raw": "{{baseUrl}}/news/{{newsId}}",
									"host": ["{{baseUrl}}"],
									"path": ["news", "{{newsId}}"]
								}
							}
						},
						{
							"name": "Delete News",
							"request": {
								"method": "DELETE",
								"header": [
									{
										"key": "Authorization",
										"value": "Bearer {{adminToken}}"
									}
								],
								"url": {
									"raw": "{{baseUrl}}/news/{{newsId}}",
									"host": ["{{baseUrl}}"],
									"path": ["news", "{{newsId}}"]
								}
							}
						},
						{
							"name": "Approve News",
							"request": {
								"method": "POST",
								"header": [
									{
										"key": "Authorization",
										"value": "Bearer {{adminToken}}"
									}
								],
								"url": {
									"raw": "{{baseUrl}}/news/{{newsId}}/approve?adminId={{adminId}}",
									"host": ["{{baseUrl}}"],
									"path": ["news", "{{newsId}}", "approve"],
									"query": [
										{
											"key": "adminId",
											"value": "{{adminId}}"
										}
									]
								}
							}
						},
						{
							"name": "Reject News",
							"request": {
								"method": "POST",
								"header": [
									{
										"key": "Authorization",
										"value": "Bearer {{adminToken}}"
									}
								],
								"url": {
									"raw": "{{baseUrl}}/news/{{newsId}}/reject?adminId={{adminId}}",
									"host": ["{{baseUrl}}"],
									"path": ["news", "{{newsId}}", "reject"],
									"query": [
										{
											"key": "adminId",
											"value": "{{adminId}}"
										}
									]
								}
							}
						},
						{
							"name": "Publish News",
							"request": {
								"method": "POST",
								"header": [
									{
										"key": "Authorization",
										"value": "Bearer {{adminToken}}"
									}
								],
								"url": {
									"raw": "{{baseUrl}}/news/{{newsId}}/publish",
									"host": ["{{baseUrl}}"],
									"path": ["news", "{{newsId}}", "publish"]
								}
							}
						},
						{
							"name": "Vote News",
							"request": {
								"method": "POST",
								"header": [
									{
										"key": "Authorization",
										"value": "Bearer {{userToken}}"
									}
								],
								"url": {
									"raw": "{{baseUrl}}/news/{{newsId}}/vote?voteType=useful",
									"host": ["{{baseUrl}}"],
									"path": ["news", "{{newsId}}", "vote"],
									"query": [
										{
											"key": "voteType",
											"value": "useful"
										}
									]
								}
							}
						},
						{
							"name": "List News by Type",
							"request": {
								"method": "GET",
								"url": {
									"raw": "{{baseUrl}}/news/type/{{newsType}}?page=0&size=10",
									"host": ["{{baseUrl}}"],
									"path": ["news", "type", "{{newsType}}"],
									"query": [
										{
											"key": "page",
											"value": "0"
										},
										{
											"key": "size",
											"value": "10"
										}
									]
								}
							}
						},
						{
							"name": "List News by User",
							"request": {
								"method": "GET",
								"header": [
									{
										"key": "Authorization",
										"value": "Bearer {{userToken}}"
									}
								],
								"url": {
									"raw": "{{baseUrl}}/news/user/{{userId}}?page=0&size=10",
									"host": ["{{baseUrl}}"],
									"path": ["news", "user", "{{userId}}"],
									"query": [
										{
											"key": "page",
											"value": "0"
										},
										{
											"key": "size",
											"value": "10"
										}
									]
								}
							}
						},
						{
							"name": "List News by Status",
							"request": {
								"method": "GET",
								"header": [
									{
										"key": "Authorization",
										"value": "Bearer {{adminToken}}"
									}
								],
								"url": {
									"raw": "{{baseUrl}}/news/status/{{status}}?page=0&size=10",
									"host": ["{{baseUrl}}"],
									"path": ["news", "status", "{{status}}"],
									"query": [
										{
											"key": "page",
											"value": "0"
										},
										{
											"key": "size",
											"value": "10"
										}
									]
								}
							}
						},
						{
							"name": "List News by Field",
							"request": {
								"method": "GET",
								"url": {
									"raw": "{{baseUrl}}/news/field/{{fieldId}}?page=0&size=10",
									"host": ["{{baseUrl}}"],
									"path": ["news", "field", "{{fieldId}}"],
									"query": [
										{
											"key": "page",
											"value": "0"
										},
										{
											"key": "size",
											"value": "10"
										}
									]
								}
							}
						},
						{
							"name": "List Published News",
							"request": {
								"method": "GET",
								"url": {
									"raw": "{{baseUrl}}/news/published/{{newsType}}?page=0&size=10",
									"host": ["{{baseUrl}}"],
									"path": ["news", "published", "{{newsType}}"],
									"query": [
										{
											"key": "page",
											"value": "0"
										},
										{
											"key": "size",
											"value": "10"
										}
									]
								}
							}
						},
						{
							"name": "List Pending Moderation",
							"request": {
								"method": "GET",
								"header": [
									{
										"key": "Authorization",
										"value": "Bearer {{adminToken}}"
									}
								],
								"url": {
									"raw": "{{baseUrl}}/news/moderation/pending?page=0&size=10",
									"host": ["{{baseUrl}}"],
									"path": ["news", "moderation", "pending"],
									"query": [
										{
											"key": "page",
											"value": "0"
										},
										{
											"key": "size",
											"value": "10"
										}
									]
								}
							}
						}
					]
				},
				{
					"name": "Recruitment Management",
					"item": [
						{
							"name": "Create Recruitment",
							"request": {
								"method": "POST",
								"header": [
									{
										"key": "Content-Type",
										"value": "application/json"
									},
									{
										"key": "Authorization",
										"value": "Bearer {{recruiterToken}}"
									}
								],
								"body": {
									"mode": "raw",
									"raw": "{\n  \"userId\": 1,\n  \"title\": \"Senior ReactJS Developer\",\n  \"content\": \"We are looking for a senior ReactJS developer with 3+ years experience\",\n  \"fieldId\": 1,\n  \"newsType\": \"RECRUITMENT\",\n  \"companyName\": \"ABC Tech\",\n  \"location\": \"Ho Chi Minh City\",\n  \"salary\": \"2000-3000 USD\",\n  \"experience\": \"3+ years\",\n  \"position\": \"Senior Developer\",\n  \"workingHours\": \"9AM-6PM\",\n  \"deadline\": \"2024-12-31\",\n  \"applicationMethod\": \"Send CV to hr@abctech.com\"\n}"
								},
								"url": {
									"raw": "{{baseUrl}}/recruitments",
									"host": ["{{baseUrl}}"],
									"path": ["recruitments"]
								}
							}
						},
						{
							"name": "List Recruitments",
							"request": {
								"method": "GET",
								"url": {
									"raw": "{{baseUrl}}/recruitments?page=0&size=10",
									"host": ["{{baseUrl}}"],
									"path": ["recruitments"],
									"query": [
										{
											"key": "page",
											"value": "0"
										},
										{
											"key": "size",
											"value": "10"
										}
									]
								}
							}
						},
						{
							"name": "List Recruitments by Company",
							"request": {
								"method": "GET",
								"url": {
									"raw": "{{baseUrl}}/recruitments/company/{{companyName}}?page=0&size=10",
									"host": ["{{baseUrl}}"],
									"path": ["recruitments", "company", "{{companyName}}"],
									"query": [
										{
											"key": "page",
											"value": "0"
										},
										{
											"key": "size",
											"value": "10"
										}
									]
								}
							}
						}
					]
				}
			]
		},
		{
			"name": "NLP Service",
			"item": [
				{
					"name": "Health Check",
					"request": {
						"method": "GET",
						"url": {
							"raw": "{{baseUrl}}/health",
							"host": ["{{baseUrl}}"],
							"path": ["health"]
						}
					}
				},
				{
					"name": "Similarity Detection",
					"item": [
						{
							"name": "Check Similarity",
							"request": {
								"method": "POST",
								"header": [
									{
										"key": "Content-Type",
										"value": "application/json"
									}
								],
								"body": {
									"mode": "raw",
									"raw": "{\n  \"text1\": \"What is machine learning?\",\n  \"text2\": \"What is ML?\"\n}"
								},
								"url": {
									"raw": "{{baseUrl}}/similarity/check",
									"host": ["{{baseUrl}}"],
									"path": ["similarity", "check"]
								}
							}
						},
						{
							"name": "Check Question Similarity",
							"request": {
								"method": "POST",
								"header": [
									{
										"key": "Content-Type",
										"value": "application/json"
									}
								],
								"body": {
									"mode": "raw",
									"raw": "{\n  \"questionText\": \"What is machine learning?\",\n  \"excludeId\": 123\n}"
								},
								"url": {
									"raw": "{{baseUrl}}/questions/similarity/check",
									"host": ["{{baseUrl}}"],
									"path": ["questions", "similarity", "check"]
								}
							}
						}
					]
				},
				{
					"name": "Essay Grading",
					"item": [
						{
							"name": "Grade Essay",
							"request": {
								"method": "POST",
								"header": [
									{
										"key": "Content-Type",
										"value": "application/json"
									}
								],
								"body": {
									"mode": "raw",
									"raw": "{\n  \"question\": \"Explain the concept of machine learning\",\n  \"answer\": \"Machine learning is a subset of artificial intelligence that enables computers to learn and improve from experience without being explicitly programmed\",\n  \"maxScore\": 100\n}"
								},
								"url": {
									"raw": "{{baseUrl}}/grading/essay",
									"host": ["{{baseUrl}}"],
									"path": ["grading", "essay"]
								}
							}
						},
						{
							"name": "Grade Exam Answer",
							"request": {
								"method": "POST",
								"header": [
									{
										"key": "Content-Type",
										"value": "application/json"
									}
								],
								"body": {
									"mode": "raw",
									"raw": "{\n  \"examId\": 1,\n  \"questionId\": 5,\n  \"answerText\": \"Student answer here...\",\n  \"maxScore\": 100\n}"
								},
								"url": {
									"raw": "{{baseUrl}}/exams/{{examId}}/questions/{{questionId}}/grade",
									"host": ["{{baseUrl}}"],
									"path": ["exams", "{{examId}}", "questions", "{{questionId}}", "grade"]
								}
							}
						},
						{
							"name": "Grade All Exam Questions",
							"request": {
								"method": "POST",
								"header": [
									{
										"key": "Content-Type",
										"value": "application/json"
									}
								],
								"body": {
									"mode": "raw",
									"raw": "{\n  \"examId\": 1\n}"
								},
								"url": {
									"raw": "{{baseUrl}}/exams/{{examId}}/grade-all",
									"host": ["{{baseUrl}}"],
									"path": ["exams", "{{examId}}", "grade-all"]
								}
							}
						}
					]
				},
				{
					"name": "Analytics",
					"item": [
						{
							"name": "Get Question Analytics",
							"request": {
								"method": "GET",
								"url": {
									"raw": "{{baseUrl}}/questions/{{questionId}}/analytics",
									"host": ["{{baseUrl}}"],
									"path": ["questions", "{{questionId}}", "analytics"]
								}
							}
						}
					]
				}
			]
		}
	],
	"variable": [
		{
			"key": "baseUrl",
			"value": "http://localhost:8080",
			"type": "string"
		},
		{
			"key": "userId",
			"value": "1",
			"type": "string"
		},
		{
			"key": "adminId",
			"value": "1",
			"type": "string"
		},
		{
			"key": "questionId",
			"value": "1",
			"type": "string"
		},
		{
			"key": "answerId",
			"value": "1",
			"type": "string"
		},
		{
			"key": "examId",
			"value": "1",
			"type": "string"
		},
		{
			"key": "resultId",
			"value": "1",
			"type": "string"
		},
		{
			"key": "registrationId",
			"value": "1",
			"type": "string"
		},
		{
			"key": "careerId",
			"value": "1",
			"type": "string"
		},
		{
			"key": "newsId",
			"value": "1",
			"type": "string"
		},
		{
			"key": "topicId",
			"value": "1",
			"type": "string"
		},
		{
			"key": "fieldId",
			"value": "1",
			"type": "string"
		},
		{
			"key": "newsType",
			"value": "NEWS",
			"type": "string"
		},
		{
			"key": "examType",
			"value": "TECHNICAL",
			"type": "string"
		},
		{
			"key": "status",
			"value": "PENDING",
			"type": "string"
		},
		{
			"key": "companyName",
			"value": "ABC Tech",
			"type": "string"
		},
		{
			"key": "token",
			"value": "",
			"type": "string"
		},
		{
			"key": "userToken",
			"value": "",
			"type": "string"
		},
		{
			"key": "adminToken",
			"value": "",
			"type": "string"
		},
		{
			"key": "recruiterToken",
			"value": "",
			"type": "string"
		}
	]
}
